raptorarima/__init__.py
raptorarima/autoregressive.py
raptorarima/differencing.py
raptorarima/movingaverage.py
raptorarima/plots.py
raptorarima-0.0.3.dist-info/LICENSE
raptorarima-0.0.3.dist-info/METADATA
raptorarima-0.0.3.dist-info/WHEEL
raptorarima-0.0.3.dist-info/top_level.txt
raptorarima-0.0.3.dist-info/RECORD
