Metadata-Version: 2.1
Name: raptorarima
Version: 0.0.3
Summary: Implementation of ARIMA model (Auto Regressive Integrated Moving Average)
Home-page: https://github.com/swaroop9ai9/raptorarima
Author: M V D SATYA SWAROOP
Author-email: swaroop9ai9@gmail.com
License: UNKNOWN
Platform: UNKNOWN
Classifier: Programming Language :: Python :: 3
Classifier: License :: OSI Approved :: MIT License
Classifier: Operating System :: OS Independent
Requires-Dist: pandas
Requires-Dist: numpy
